targetprocess/__init__.py
targetprocess/api.py
targetprocess/exceptions.py
targetprocess/serializers.py
targetprocess_client-0.1.2.dist-info/DESCRIPTION.rst
targetprocess_client-0.1.2.dist-info/METADATA
targetprocess_client-0.1.2.dist-info/metadata.json
targetprocess_client-0.1.2.dist-info/RECORD
targetprocess_client-0.1.2.dist-info/top_level.txt
targetprocess_client-0.1.2.dist-info/WHEEL
