Metadata-Version: 2.0
Name: targetprocess-client
Version: 0.1.2
Summary: Python library to help getting data from TargetProcess API
Home-page: https://github.com/magicjohnson/targetprocess-client
Author: Dmitriy Trochshenko
Author-email: dmitriy.trochshenko@gmail.com
License: MIT
Download-URL: https://github.com/magicjohnson/targetprocess-client/archive/v0.1.2.zip
Keywords: targetprocess api
Platform: UNKNOWN
Classifier: Development Status :: 4 - Beta
Classifier: Intended Audience :: Developers
Classifier: Operating System :: OS Independent
Classifier: Topic :: Software Development :: Libraries :: Python Modules
Classifier: Topic :: Internet
Classifier: License :: OSI Approved :: MIT License
Classifier: Programming Language :: Python
Classifier: Programming Language :: Python :: 2
Classifier: Programming Language :: Python :: 2.7
Classifier: Programming Language :: Python :: 3
Classifier: Programming Language :: Python :: 3.3
Classifier: Programming Language :: Python :: 3.4
Classifier: Programming Language :: Python :: 3.5
Requires-Dist: pytz
Requires-Dist: requests
Requires-Dist: six
